HXMK/__init__.py
HXMK/__main__.py
HXMK/coloring.py
HXMK/environment.py
HXMK/pattern_parser.py
HXMK-0.0.9.dist-info/LICENSE.md
HXMK-0.0.9.dist-info/METADATA
HXMK-0.0.9.dist-info/WHEEL
HXMK-0.0.9.dist-info/entry_points.txt
HXMK-0.0.9.dist-info/top_level.txt
HXMK-0.0.9.dist-info/RECORD
