Metadata-Version: 2.1
Name: HXMK
Version: 0.0.9
Summary: A Python-based build system with a Makefile-like experience
Home-page: https://github.com/Hexcell/HXMK.git
Author: Hexcell
Author-email: fabian0010k@gmail.com
License: UNKNOWN
Platform: UNKNOWN
Classifier: Programming Language :: Python :: 3
Classifier: License :: OSI Approved :: MIT License
Classifier: Operating System :: OS Independent
Requires-Dist: colorama (>=0.4.1)
